{"308": [[482, 68]], "482": [[308, null]], "87": [[406, 66]], "406": [[87, null], [55, 63]], "129": [[1221, 136]], "1221": [[129, null]], "58": [[550, 78]], "550": [[58, null]], "80": [[832, 79]], "832": [[80, null]], "181": [[1509, 37]], "1509": [[181, null]], "418": [[587, 39]], "587": [[418, null]], "464": [[1471, 106]], "1471": [[464, null]], "1": [[1286, 111], [81, null]], "1286": [[1, null]], "350": [[1228, 17]], "1228": [[350, null]], "53": [[848, 162]], "848": [[53, null]], "417": [[1851, 170]], "1851": [[417, null]], "149": [[480, 93]], "480": [[149, null]], "273": [[1512, 92]], "1512": [[273, null]], "2": [[531, 94]], "531": [[2, null]], "98": [[725, 160]], "725": [[98, null]], "99": [[1093, 158]], "1093": [[99, null]], "984": [[1122, 72]], "1122": [[984, null]], "104": [[1804, 71]], "1804": [[104, null]], "47": [[1231, 182]], "1231": [[47, null]], "122": [[1268, 184]], "1268": [[122, null]], "27": [[789, 56]], "789": [[27, null]], "18": [[549, 53]], "549": [[18, null]], "500": [[395, 57]], "395": [[500, null]], "3": [[1814, 6], [67, null]], "1814": [[3, null]], "50": [[1194, 8]], "1194": [[50, null]], "67": [[3, 9]], "178": [[709, 108]], "709": [[178, null]], "82": [[1200, 30]], "1200": [[82, null]], "130": [[1141, 29]], "1141": [[130, null]], "247": [[1079, 31]], "1079": [[247, null]], "559": [[1553, 132]], "1553": [[559, null]], "238": [[1761, 126]], "1761": [[238, null]], "94": [[1087, 133]], "1087": [[94, null]], "11": [[1159, 152]], "1159": [[11, null]], "0": [[1110, 153]], "1110": [[0, null]], "4": [[1611, 145]], "1611": [[4, null]], "70": [[1255, 87]], "1255": [[70, null]], "71": [[477, 86]], "477": [[71, null]], "17": [[1319, 88]], "1319": [[17, null]], "105": [[1160, 51]], "1160": [[105, null]], "153": [[1354, 47]], "1354": [[153, null]], "29": [[404, 69]], "404": [[29, null]], "85": [[222, 70]], "222": [[85, null]], "28": [[1644, 27]], "1644": [[28, null]], "117": [[1683, 26]], "1683": [[117, null]], "297": [[283, 181]], "283": [[297, null]], "75": [[1542, 178]], "1542": [[75, null]], "111": [[371, 1]], "371": [[111, null]], "83": [[20, 112]], "20": [[83, null], [1594, 107]], "1594": [[20, null]], "13": [[364, 113]], "364": [[13, null]], "250": [[1446, 167]], "1446": [[250, null]], "62": [[554, 168]], "554": [[62, null]], "374": [[1528, 169]], "1528": [[374, null]], "23": [[1727, 161]], "1727": [[23, null]], "39": [[925, 33]], "925": [[39, null]], "161": [[1738, 36]], "1738": [[161, null]], "76": [[1652, 173]], "1652": [[76, null]], "57": [[534, 174]], "534": [[57, null]], "12": [[455, 7]], "455": [[12, null]], "314": [[814, 4]], "814": [[314, null]], "133": [[357, 13]], "357": [[133, null]], "209": [[227, 14], [120, null]], "227": [[209, null]], "210": [[1659, 11]], "1659": [[210, null]], "10": [[1679, 124], [8, null], [189, null]], "1679": [[10, null]], "8": [[10, 128]], "189": [[10, 129]], "92": [[1758, 138]], "1758": [[92, null]], "93": [[427, 146]], "427": [[93, null]], "107": [[568, 131]], "568": [[107, null]], "44": [[967, 139]], "967": [[44, null]], "54": [[739, 105]], "739": [[54, null]], "56": [[801, 121]], "801": [[56, null]], "245": [[1026, 116]], "1026": [[245, null]], "206": [[1621, 122]], "1621": [[206, null]], "103": [[663, 40]], "663": [[103, null]], "38": [[1819, 42]], "1819": [[38, null], [31, null]], "31": [[1819, 43]], "231": [[958, 80]], "958": [[231, null]], "253": [[302, 159]], "302": [[253, null]], "15": [[291, 165]], "291": [[15, null]], "279": [[661, 166]], "661": [[279, null]], "174": [[1280, 149]], "1280": [[174, null]], "95": [[1808, 155]], "1808": [[95, null]], "185": [[1561, 65]], "1561": [[185, null]], "34": [[1629, 52]], "1629": [[34, null]], "242": [[633, 89]], "633": [[242, null]], "332": [[1138, 90]], "1138": [[332, null]], "170": [[767, 20]], "767": [[170, null], [79, null]], "79": [[767, 21]], "43": [[1477, 15]], "1477": [[43, null]], "171": [[1500, 60]], "1500": [[171, null]], "55": [[1847, 62], [285, null], [406, null]], "1847": [[55, null]], "344": [[319, 76]], "319": [[344, null], [16, 75]], "16": [[319, null], [1232, 74]], "282": [[1669, 114]], "1669": [[282, null]], "312": [[1181, 109]], "1181": [[312, null]], "77": [[938, 115]], "938": [[77, null]], "327": [[177, 10]], "177": [[327, null]], "65": [[1658, 12], [386, null]], "1658": [[65, null]], "232": [[703, 163]], "703": [[232, null]], "9": [[930, 183]], "930": [[9, null]], "48": [[1357, 180]], "1357": [[48, null]], "40": [[1233, 85]], "1233": [[40, null]], "561": [[286, 83]], "286": [[561, null], [26, null]], "453": [[1634, 185]], "1634": [[453, null]], "64": [[1298, 18]], "1298": [[64, null]], "219": [[994, 23]], "994": [[219, null]], "22": [[686, 171]], "686": [[22, null]], "199": [[215, 35]], "215": [[199, null]], "148": [[1102, 175]], "1102": [[148, null]], "74": [[474, 176], [7, null]], "474": [[74, null]], "42": [[402, 91]], "402": [[42, null]], "135": [[212, 150]], "212": [[135, null]], "274": [[1431, 24]], "1431": [[274, null]], "120": [[209, 19]], "6": [[515, 2]], "515": [[6, null]], "45": [[512, 3]], "512": [[45, null]], "439": [[1583, 5]], "1583": [[439, null]], "459": [[193, 59]], "193": [[459, null]], "299": [[1052, 96]], "1052": [[299, null]], "403": [[1148, 98]], "1148": [[403, null]], "186": [[356, 99], [469, null]], "356": [[186, null]], "66": [[738, 164]], "738": [[66, null]], "485": [[1072, 58], [32, null]], "1072": [[485, null]], "194": [[1427, 55]], "1427": [[194, null]], "665": [[1660, 147]], "1660": [[665, null]], "26": [[286, 82]], "49": [[1220, 84]], "1220": [[49, null]], "175": [[84, 100]], "84": [[175, null], [696, 97]], "1232": [[16, null]], "24": [[1080, 73]], "1080": [[24, null]], "504": [[1120, 48]], "1120": [[504, null]], "211": [[1259, 22]], "1259": [[211, null]], "386": [[65, 16]], "121": [[294, 119]], "294": [[121, null]], "86": [[1619, 127]], "1619": [[86, null]], "779": [[990, 123]], "990": [[779, null]], "285": [[55, 64]], "223": [[736, 67]], "736": [[223, null]], "73": [[290, 25]], "290": [[73, null]], "32": [[485, 61]], "469": [[186, 103]], "198": [[733, 140]], "733": [[198, null], [37, null]], "37": [[733, 141]], "192": [[1682, 110]], "1682": [[192, null]], "187": [[1004, 104]], "1004": [[187, null]], "141": [[1578, 130]], "1578": [[141, null]], "25": [[483, 135]], "483": [[25, null]], "365": [[1180, 172]], "1180": [[365, null]], "349": [[637, 156]], "637": [[349, null]], "139": [[1124, 28]], "1124": [[139, null]], "7": [[74, 177]], "14": [[1284, 151]], "1284": [[14, null]], "221": [[1599, 157]], "1599": [[221, null]], "114": [[435, 32]], "435": [[114, null]], "21": [[1827, 34]], "1827": [[21, null]], "63": [[602, 179]], "602": [[63, null]], "147": [[1560, 77]], "1560": [[147, null]], "143": [[1728, 134]], "1728": [[143, null]], "202": [[833, 144]], "833": [[202, null]], "260": [[134, 120]], "134": [[260, null]], "868": [[1674, 142]], "1674": [[868, null]], "36": [[1478, 143]], "1478": [[36, null]], "183": [[1493, 154]], "1493": [[183, null]], "145": [[1779, 54]], "1779": [[145, null]], "157": [[1798, 137]], "1798": [[157, null]], "409": [[1730, 148]], "1730": [[409, null]], "127": [[1111, 41]], "1111": [[127, null]], "259": [[1149, 44]], "1149": [[259, null]], "144": [[1757, 45]], "1757": [[144, null]], "328": [[1187, 46]], "1187": [[328, null]], "152": [[255, 102]], "255": [[152, null]], "19": [[1283, 81]], "1283": [[19, null]], "696": [[84, null]], "51": [[1705, 101]], "1705": [[51, null]], "41": [[857, 95]], "857": [[41, null]], "426": [[970, 49]], "970": [[426, null]], "295": [[821, 118]], "821": [[295, null]], "5": [[1323, 125]], "1323": [[5, null]], "35": [[949, 38]], "949": [[35, null]], "81": [[1, 117]], "126": [[310, 50]], "310": [[126, null]]}